your_package/__init__.py
your_package/module.py
pasgenkan-1.0.0.dist-info/METADATA
pasgenkan-1.0.0.dist-info/WHEEL
pasgenkan-1.0.0.dist-info/top_level.txt
pasgenkan-1.0.0.dist-info/RECORD
